{"v":"5.6.5","fr":12,"ip":0,"op":60,"w":500,"h":500,"nm":"giraffe","ddd":0,"assets":[],"layers":[{"ddd":0,"ind":1,"ty":4,"nm":"Horn L Outlines","parent":5,"sr":1,"ks":{"o":{"a":0,"k":100,"ix":11},"r":{"a":0,"k":0,"ix":10},"p":{"a":0,"k":[53.4,4.45,0],"ix":2},"a":{"a":0,"k":[4,26.25,0],"ix":1},"s":{"a":0,"k":[100,100,100],"ix":6}},"ao":0,"shapes":[{"ty":"gr","it":[{"ind":0,"ty":"sh","ix":1,"ks":{"a":0,"k":{"i":[[0,0],[-2.2,8],[0.1,0.6],[1,0.5],[1.1,0.1],[0.6,-0.7],[0.1,-0.5],[1.8,-9]],"o":[[3.2,-7.7],[0.2,-0.7],[-0.2,-1.1],[-1,-0.5],[-0.9,-0.1],[-0.3,0.4],[-2.1,9],[0,0]],"v":[[-1.25,14.3],[6.85,-9.2],[7.15,-11.2],[5.05,-13.7],[1.75,-14.4],[-0.95,-13.8],[-1.45,-12.5],[-7.25,14.5]],"c":true},"ix":2},"nm":"Path 1","mn":"ADBE Vector Shape - Group","hd":false},{"ty":"fl","c":{"a":0,"k":[1,1,1,1],"ix":4},"o":{"a":0,"k":100,"ix":5},"r":1,"bm":0,"nm":"Fill 1","mn":"ADBE Vector Graphic - Fill","hd":false},{"ty":"tr","p":{"a":0,"k":[7.5,14.75],"ix":2},"a":{"a":0,"k":[0,0],"ix":1},"s":{"a":0,"k":[100,100],"ix":3},"r":{"a":0,"k":0,"ix":6},"o":{"a":0,"k":100,"ix":7},"sk":{"a":0,"k":0,"ix":4},"sa":{"a":0,"k":0,"ix":5},"nm":"Transform"}],"nm":"Group 1","np":2,"cix":2,"bm":0,"ix":1,"mn":"ADBE Vector Group","hd":false}],"ip":0,"op":77,"st":0,"bm":0},{"ddd":0,"ind":2,"ty":4,"nm":"Horn R Outlines","parent":5,"sr":1,"ks":{"o":{"a":0,"k":80,"ix":11},"r":{"a":0,"k":0,"ix":10},"p":{"a":0,"k":[41.55,4.2,0],"ix":2},"a":{"a":0,"k":[3.15,20.5,0],"ix":1},"s":{"a":0,"k":[100,100,100],"ix":6}},"ao":0,"shapes":[{"ty":"gr","it":[{"ind":0,"ty":"sh","ix":1,"ks":{"a":0,"k":{"i":[[0,0],[-1.5,7.2],[0.5,0.3],[0.3,0],[0,0],[0.5,-0.3],[0.1,-0.5],[0.9,-7.6]],"o":[[2.4,-7],[0.1,-0.5],[-0.3,-0.2],[0,0],[-0.5,0],[-0.4,0.4],[-1.6,7.5],[0,0]],"v":[[-0.6,10.75],[5.2,-10.55],[4.9,-12.05],[4,-12.25],[0.6,-12.25],[-1,-11.95],[-1.7,-10.45],[-5.4,12.25]],"c":true},"ix":2},"nm":"Path 1","mn":"ADBE Vector Shape - Group","hd":false},{"ty":"fl","c":{"a":0,"k":[1,1,1,1],"ix":4},"o":{"a":0,"k":100,"ix":5},"r":1,"bm":0,"nm":"Fill 1","mn":"ADBE Vector Graphic - Fill","hd":false},{"ty":"tr","p":{"a":0,"k":[5.65,12.5],"ix":2},"a":{"a":0,"k":[0,0],"ix":1},"s":{"a":0,"k":[100,100],"ix":3},"r":{"a":0,"k":0,"ix":6},"o":{"a":0,"k":100,"ix":7},"sk":{"a":0,"k":0,"ix":4},"sa":{"a":0,"k":0,"ix":5},"nm":"Transform"}],"nm":"Group 1","np":2,"cix":2,"bm":0,"ix":1,"mn":"ADBE Vector Group","hd":false}],"ip":0,"op":77,"st":0,"bm":0},{"ddd":0,"ind":3,"ty":4,"nm":"Ear L Outlines","parent":5,"sr":1,"ks":{"o":{"a":0,"k":100,"ix":11},"r":{"a":0,"k":0,"ix":10},"p":{"a":0,"k":[61.8,12.05,0],"ix":2},"a":{"a":0,"k":[5.7,25.45,0],"ix":1},"s":{"a":0,"k":[100,100,100],"ix":6}},"ao":0,"shapes":[{"ty":"gr","it":[{"ind":0,"ty":"sh","ix":1,"ks":{"a":0,"k":{"i":[[0,0],[-10.3,8.9],[2.8,-4.8],[5.2,-2.1],[5.6,-0.2]],"o":[[12.5,-5.6],[2.5,5],[-2.8,4.8],[-5.2,2.1],[0,0]],"v":[[-18.45,7.3],[15.95,-14.7],[15.05,1.3],[2.35,11.7],[-14.05,14.7]],"c":true},"ix":2},"nm":"Path 1","mn":"ADBE Vector Shape - Group","hd":false},{"ty":"fl","c":{"a":0,"k":[1,1,1,1],"ix":4},"o":{"a":0,"k":100,"ix":5},"r":1,"bm":0,"nm":"Fill 1","mn":"ADBE Vector Graphic - Fill","hd":false},{"ty":"tr","p":{"a":0,"k":[18.7,14.95],"ix":2},"a":{"a":0,"k":[0,0],"ix":1},"s":{"a":0,"k":[100,100],"ix":3},"r":{"a":0,"k":0,"ix":6},"o":{"a":0,"k":100,"ix":7},"sk":{"a":0,"k":0,"ix":4},"sa":{"a":0,"k":0,"ix":5},"nm":"Transform"}],"nm":"Group 1","np":2,"cix":2,"bm":0,"ix":1,"mn":"ADBE Vector Group","hd":false}],"ip":0,"op":77,"st":0,"bm":0},{"ddd":0,"ind":4,"ty":4,"nm":"Ear R Outlines","parent":5,"sr":1,"ks":{"o":{"a":0,"k":70,"ix":11},"r":{"a":0,"k":0,"ix":10},"p":{"a":0,"k":[29.6,9,0],"ix":2},"a":{"a":0,"k":[17,11.6,0],"ix":1},"s":{"a":0,"k":[100,100,100],"ix":6}},"ao":0,"shapes":[{"ty":"gr","it":[{"ind":0,"ty":"sh","ix":1,"ks":{"a":0,"k":{"i":[[0,0],[6.7,4.2],[-3,-2.6],[-4,-0.1]],"o":[[-8,-0.6],[0.5,4],[3,2.7],[0,0]],"v":[[11.25,-0.05],[-11.25,-7.35],[-5.85,3.05],[5.05,7.35]],"c":true},"ix":2},"nm":"Path 1","mn":"ADBE Vector Shape - Group","hd":false},{"ty":"fl","c":{"a":0,"k":[1,1,1,1],"ix":4},"o":{"a":0,"k":100,"ix":5},"r":1,"bm":0,"nm":"Fill 1","mn":"ADBE Vector Graphic - Fill","hd":false},{"ty":"tr","p":{"a":0,"k":[11.5,7.6],"ix":2},"a":{"a":0,"k":[0,0],"ix":1},"s":{"a":0,"k":[100,100],"ix":3},"r":{"a":0,"k":0,"ix":6},"o":{"a":0,"k":100,"ix":7},"sk":{"a":0,"k":0,"ix":4},"sa":{"a":0,"k":0,"ix":5},"nm":"Transform"}],"nm":"Group 1","np":2,"cix":2,"bm":0,"ix":1,"mn":"ADBE Vector Group","hd":false}],"ip":0,"op":77,"st":0,"bm":0},{"ddd":0,"ind":5,"ty":4,"nm":"Head Outlines","parent":6,"sr":1,"ks":{"o":{"a":0,"k":100,"ix":11},"r":{"a":1,"k":[{"i":{"x":[0.667],"y":[1]},"o":{"x":[0.333],"y":[0]},"t":16,"s":[0]},{"i":{"x":[0.667],"y":[1]},"o":{"x":[0.333],"y":[0]},"t":19,"s":[22]},{"i":{"x":[0.667],"y":[1]},"o":{"x":[0.333],"y":[0]},"t":24,"s":[22]},{"i":{"x":[0.667],"y":[1]},"o":{"x":[0.333],"y":[0]},"t":28,"s":[18]},{"i":{"x":[0.667],"y":[1]},"o":{"x":[0.333],"y":[0]},"t":32,"s":[22]},{"t":37,"s":[0]}],"ix":10},"p":{"a":0,"k":[10.95,15.75,0],"ix":2},"a":{"a":0,"k":[68.05,23.85,0],"ix":1},"s":{"a":0,"k":[100,100,100],"ix":6}},"ao":0,"shapes":[{"ty":"gr","it":[{"ind":0,"ty":"sh","ix":1,"ks":{"a":0,"k":{"i":[[3.6,1.9],[11.6,-0.3],[4.2,-10.9],[3.3,-5.4],[2.3,-3.1],[-1.4,-6.1],[-1.9,-1.1],[-1.2,-0.1],[-3.6,1.7],[-16.2,7.6],[-3.7,3.5],[0.4,5.1]],"o":[[-10.3,-5.4],[-11.6,0.3],[-2.3,5.9],[-2.1,3.3],[-3.7,4.9],[0.5,2.2],[1,0.6],[4,0.2],[16.2,-7.6],[4.6,-2.1],[3.7,-3.4],[0,0]],"v":[[35.6,-24.7],[2.4,-34.3],[-25.6,-16.8],[-31.1,1.4],[-38.7,10.3],[-42.4,27.9],[-39,33.5],[-35.6,34.4],[-24.3,31.2],[24.3,8.5],[37.3,0.7],[43.4,-12.7]],"c":true},"ix":2},"nm":"Path 1","mn":"ADBE Vector Shape - Group","hd":false},{"ty":"fl","c":{"a":0,"k":[1,1,1,1],"ix":4},"o":{"a":0,"k":100,"ix":5},"r":1,"bm":0,"nm":"Fill 1","mn":"ADBE Vector Graphic - Fill","hd":false},{"ty":"tr","p":{"a":0,"k":[44.05,34.85],"ix":2},"a":{"a":0,"k":[0,0],"ix":1},"s":{"a":0,"k":[100,100],"ix":3},"r":{"a":0,"k":0,"ix":6},"o":{"a":0,"k":100,"ix":7},"sk":{"a":0,"k":0,"ix":4},"sa":{"a":0,"k":0,"ix":5},"nm":"Transform"}],"nm":"Group 1","np":2,"cix":2,"bm":0,"ix":1,"mn":"ADBE Vector Group","hd":false}],"ip":0,"op":77,"st":0,"bm":0},{"ddd":0,"ind":6,"ty":4,"nm":"Neck 2 Outlines","parent":7,"sr":1,"ks":{"o":{"a":0,"k":100,"ix":11},"r":{"a":1,"k":[{"i":{"x":[0.667],"y":[1]},"o":{"x":[0.333],"y":[0]},"t":14,"s":[0]},{"i":{"x":[0.667],"y":[1]},"o":{"x":[0.333],"y":[0]},"t":17,"s":[-7]},{"i":{"x":[0.667],"y":[1]},"o":{"x":[0.333],"y":[0]},"t":35,"s":[-7]},{"t":38,"s":[0]}],"ix":10},"p":{"a":0,"k":[73.25,46.05,0],"ix":2},"a":{"a":0,"k":[112.15,155.25,0],"ix":1},"s":{"a":0,"k":[100,100,100],"ix":6}},"ao":0,"shapes":[{"ty":"gr","it":[{"ind":0,"ty":"sh","ix":1,"ks":{"a":0,"k":{"i":[[0,0],[8.2,23.5],[6.3,17.2],[3.5,21.4],[-1.9,2.5],[-2.6,0.6],[-6.5,-3.4],[-2.6,-2.7],[-13.7,-29.4],[-4.9,-8.2],[-7.8,-13.7],[0,-2.4],[2.7,-2.4],[7.9,-3]],"o":[[-20.6,-14],[-6,-17.2],[-7.5,-20.4],[-0.5,-3.1],[1.6,-2.1],[7.1,-1.7],[3.3,1.7],[22.5,23.4],[4,8.6],[8.1,13.5],[1.2,2.1],[-0.1,3.6],[-6.3,5.6],[0,0]],"v":[[16.3,93],[-28.4,34.9],[-42.7,-18],[-67.2,-78.1],[-66,-87.1],[-59.1,-90.6],[-37.7,-89.6],[-29.1,-82.5],[25.8,-2.5],[38.4,23.2],[65.6,61.7],[67.9,68.5],[62.4,77.5],[41,90.5]],"c":true},"ix":2},"nm":"Path 1","mn":"ADBE Vector Shape - Group","hd":false},{"ty":"fl","c":{"a":0,"k":[1,1,1,1],"ix":4},"o":{"a":0,"k":100,"ix":5},"r":1,"bm":0,"nm":"Fill 1","mn":"ADBE Vector Graphic - Fill","hd":false},{"ty":"tr","p":{"a":0,"k":[68.15,93.25],"ix":2},"a":{"a":0,"k":[0,0],"ix":1},"s":{"a":0,"k":[100,100],"ix":3},"r":{"a":0,"k":0,"ix":6},"o":{"a":0,"k":100,"ix":7},"sk":{"a":0,"k":0,"ix":4},"sa":{"a":0,"k":0,"ix":5},"nm":"Transform"}],"nm":"Group 1","np":2,"cix":2,"bm":0,"ix":1,"mn":"ADBE Vector Group","hd":false}],"ip":0,"op":77,"st":0,"bm":0},{"ddd":0,"ind":7,"ty":4,"nm":"Neck 1 Outlines","parent":13,"sr":1,"ks":{"o":{"a":0,"k":100,"ix":11},"r":{"a":1,"k":[{"i":{"x":[0.667],"y":[1]},"o":{"x":[0.333],"y":[0]},"t":11,"s":[0]},{"i":{"x":[0.667],"y":[1]},"o":{"x":[0.333],"y":[0]},"t":14,"s":[-7]},{"i":{"x":[0.667],"y":[1]},"o":{"x":[0.333],"y":[0]},"t":37,"s":[-7]},{"t":40,"s":[0]}],"ix":10},"p":{"a":0,"k":[92.35,63.95,0],"ix":2},"a":{"a":0,"k":[109.55,94.95,0],"ix":1},"s":{"a":0,"k":[100,100,100],"ix":6}},"ao":0,"shapes":[{"ty":"gr","it":[{"ind":0,"ty":"sh","ix":1,"ks":{"a":0,"k":{"i":[[4.51,10.356],[6.6,10.7],[2.7,5.3],[0.9,7.4],[-2.8,4],[-5.7,0.5],[-15.7,-11.6],[-7.4,-9],[-12.5,-9.5],[-1.5,-5.9],[4,-3.899],[5.201,-1.9],[18.799,2.9]],"o":[[-4.511,-10.356],[-3.1,-5],[-3.4,-6.7],[-0.6,-4.8],[3.2,-4.6],[19.5,-1.5],[9.4,6.9],[10,12.1],[4.799,3.7],[1.4,5.4],[-4,3.9],[-17.899,6.5],[0,0]],"v":[[-51.9,35.9],[-57.1,0.8],[-65.8,-15],[-71.2,-36.8],[-69.5,-51],[-54.3,-57.2],[1.7,-45],[25.3,-19.3],[59.2,13.2],[70.9,26.7],[65.9,41.9],[51.499,50.2],[-4.8,55.8]],"c":true},"ix":2},"nm":"Path 1","mn":"ADBE Vector Shape - Group","hd":false},{"ty":"fl","c":{"a":0,"k":[1,1,1,1],"ix":4},"o":{"a":0,"k":100,"ix":5},"r":1,"bm":0,"nm":"Fill 1","mn":"ADBE Vector Graphic - Fill","hd":false},{"ty":"tr","p":{"a":0,"k":[72.55,58.95],"ix":2},"a":{"a":0,"k":[0,0],"ix":1},"s":{"a":0,"k":[100,100],"ix":3},"r":{"a":0,"k":0,"ix":6},"o":{"a":0,"k":100,"ix":7},"sk":{"a":0,"k":0,"ix":4},"sa":{"a":0,"k":0,"ix":5},"nm":"Transform"}],"nm":"Group 1","np":2,"cix":2,"bm":0,"ix":1,"mn":"ADBE Vector Group","hd":false}],"ip":0,"op":77,"st":0,"bm":0},{"ddd":0,"ind":8,"ty":4,"nm":"Tail Outlines","parent":13,"sr":1,"ks":{"o":{"a":0,"k":80,"ix":11},"r":{"a":1,"k":[{"i":{"x":[0.667],"y":[1]},"o":{"x":[0.333],"y":[0]},"t":0,"s":[23]},{"i":{"x":[0.667],"y":[1]},"o":{"x":[0.333],"y":[0]},"t":13,"s":[-6]},{"i":{"x":[0.667],"y":[1]},"o":{"x":[0.333],"y":[0]},"t":15,"s":[-6]},{"i":{"x":[0.667],"y":[1]},"o":{"x":[0.333],"y":[0]},"t":29,"s":[26]},{"i":{"x":[0.667],"y":[1]},"o":{"x":[0.333],"y":[0]},"t":43,"s":[-6]},{"t":60,"s":[23]}],"ix":10},"p":{"a":0,"k":[200.35,64.3,0],"ix":2},"a":{"a":0,"k":[7.35,7.3,0],"ix":1},"s":{"a":0,"k":[100,100,100],"ix":6}},"ao":0,"shapes":[{"ty":"gr","it":[{"ind":0,"ty":"sh","ix":1,"ks":{"a":0,"k":{"i":[[0,0],[-1.799,-6.3],[-7.299,-18.701],[-1.5,-1.9],[-2.199,-1.9],[-0.7,-11.701],[-5.601,-10.4],[4.599,7.1],[0.099,13.201],[0.8,4.1],[1,2.6],[9.099,24.401]],"o":[[4.199,4.899],[5.3,19.4],[0.901,2.2],[1.801,2.2],[9,7.6],[0.7,11.7],[-7.901,-2.9],[-7.201,-11],[0,-4.199],[-0.5,-2.8],[-9.101,-24.4],[0,0]],"v":[[-22.2,-77.05],[-14.301,-59.45],[2.199,-1.45],[5.499,4.95],[11.999,10.45],[24.1,42.55],[30.1,77.05],[11.4,60.65],[0.1,23.349],[-0.4,10.95],[-2.9,2.95],[-30.1,-70.151]],"c":true},"ix":2},"nm":"Path 1","mn":"ADBE Vector Shape - Group","hd":false},{"ty":"fl","c":{"a":0,"k":[1,1,1,1],"ix":4},"o":{"a":0,"k":100,"ix":5},"r":1,"bm":0,"nm":"Fill 1","mn":"ADBE Vector Graphic - Fill","hd":false},{"ty":"tr","p":{"a":0,"k":[30.35,77.3],"ix":2},"a":{"a":0,"k":[0,0],"ix":1},"s":{"a":0,"k":[100,100],"ix":3},"r":{"a":0,"k":0,"ix":6},"o":{"a":0,"k":100,"ix":7},"sk":{"a":0,"k":0,"ix":4},"sa":{"a":0,"k":0,"ix":5},"nm":"Transform"}],"nm":"Group 1","np":2,"cix":2,"bm":0,"ix":1,"mn":"ADBE Vector Group","hd":false}],"ip":0,"op":77,"st":0,"bm":0},{"ddd":0,"ind":9,"ty":4,"nm":"Arm L Outlines","sr":1,"ks":{"o":{"a":0,"k":100,"ix":11},"r":{"a":0,"k":0,"ix":10},"p":{"a":0,"k":[238.75,463.25,0],"ix":2},"a":{"a":0,"k":[25.7,195.5,0],"ix":1},"s":{"a":0,"k":[100,100,100],"ix":6}},"ao":0,"shapes":[{"ty":"gr","it":[{"ind":0,"ty":"sh","ix":1,"ks":{"a":0,"k":{"i":[[0,0],[0.7,-26.8],[0.6,-5.5],[0.8,-6],[-0.2,-9.699],[-0.3,-15.601],[0.6,-1.099],[1.3,-0.601],[3.8,0.2],[1.8,3.1],[-0.4,3.6],[-0.4,5.8],[0.9,21.901],[0.3,6.5],[1,7.3],[1.6,7.6],[-0.3,16.4]],"o":[[-0.601,26.8],[-0.1,5.599],[-0.7,6],[-1.2,9.699],[0.4,15.5],[0,1.3],[-0.7,1.301],[-3.5,1.6],[-3.3,-0.201],[-1.8,-3],[0.7,-5.8],[1.5,-21.9],[-0.3,-6.599],[-0.3,-7.301],[-1.1,-7.6],[-3.4,-16],[0,0]],"v":[[23.95,-89.05],[12.95,-19.25],[12.95,-1.651],[11.05,16.15],[10.25,50.349],[14.05,96.95],[13.55,100.849],[10.35,103.45],[-0.75,105.55],[-9.55,101.15],[-10.45,90.55],[-8.75,73.15],[-8.95,7.349],[-9.75,-9.35],[-11.55,-29.35],[-19.05,-56.95],[-23.65,-105.75]],"c":true},"ix":2},"nm":"Path 1","mn":"ADBE Vector Shape - Group","hd":false},{"ty":"fl","c":{"a":0,"k":[1,1,1,1],"ix":4},"o":{"a":0,"k":100,"ix":5},"r":1,"bm":0,"nm":"Fill 1","mn":"ADBE Vector Graphic - Fill","hd":false},{"ty":"tr","p":{"a":0,"k":[24.2,106],"ix":2},"a":{"a":0,"k":[0,0],"ix":1},"s":{"a":0,"k":[100,100],"ix":3},"r":{"a":0,"k":0,"ix":6},"o":{"a":0,"k":100,"ix":7},"sk":{"a":0,"k":0,"ix":4},"sa":{"a":0,"k":0,"ix":5},"nm":"Transform"}],"nm":"Group 1","np":2,"cix":2,"bm":0,"ix":1,"mn":"ADBE Vector Group","hd":false}],"ip":0,"op":77,"st":0,"bm":0},{"ddd":0,"ind":10,"ty":4,"nm":"Arm R Outlines","sr":1,"ks":{"o":{"a":0,"k":70,"ix":11},"r":{"a":0,"k":0,"ix":10},"p":{"a":0,"k":[216.45,452.55,0],"ix":2},"a":{"a":0,"k":[27.1,203.9,0],"ix":1},"s":{"a":0,"k":[100,100,100],"ix":6}},"ao":0,"shapes":[{"ty":"gr","it":[{"ind":0,"ty":"sh","ix":1,"ks":{"a":0,"k":{"i":[[0,0],[-3.4,-23.6],[-0.7,-8.6],[-1,-12.2],[-0.1,-11.4],[1.4,-14.6],[-0.5,-1.1],[-1.8,-0.2],[-2.1,4.5],[0.5,2.5],[1,6.5],[-0.3,22.7],[0,5.5],[-0.3,6.5],[-0.9,8.3],[-1.3,11.4]],"o":[[-0.2,23.9],[1.3,8.5],[1,12.3],[0.9,11.3],[0.1,14.6],[-0.1,1.2],[0.9,1.7],[4.5,0.4],[1,-2.3],[-1.1,-6.6],[-3.9,-24.3],[0.1,-5.5],[0.1,-6.5],[0.5,-8.3],[1.3,-11.4],[0,0]],"v":[[-19.65,-108.65],[-8.65,-38.15],[-6.05,-12.35],[-3.05,24.45],[-1.95,58.55],[-3.75,102.35],[-3.45,106.05],[1.25,108.25],[18.85,103.85],[19.15,96.35],[16.85,77.05],[12.95,9.25],[14.95,-7.15],[14.55,-26.75],[17.65,-51.65],[15.35,-85.85]],"c":true},"ix":2},"nm":"Path 1","mn":"ADBE Vector Shape - Group","hd":false},{"ty":"fl","c":{"a":0,"k":[1,1,1,1],"ix":4},"o":{"a":0,"k":100,"ix":5},"r":1,"bm":0,"nm":"Fill 1","mn":"ADBE Vector Graphic - Fill","hd":false},{"ty":"tr","p":{"a":0,"k":[20.1,108.9],"ix":2},"a":{"a":0,"k":[0,0],"ix":1},"s":{"a":0,"k":[100,100],"ix":3},"r":{"a":0,"k":0,"ix":6},"o":{"a":0,"k":100,"ix":7},"sk":{"a":0,"k":0,"ix":4},"sa":{"a":0,"k":0,"ix":5},"nm":"Transform"}],"nm":"Group 1","np":2,"cix":2,"bm":0,"ix":1,"mn":"ADBE Vector Group","hd":false}],"ip":0,"op":77,"st":0,"bm":0},{"ddd":0,"ind":11,"ty":4,"nm":"Leg L Outlines","sr":1,"ks":{"o":{"a":0,"k":100,"ix":11},"r":{"a":1,"k":[{"i":{"x":[0.667],"y":[1]},"o":{"x":[0.333],"y":[0]},"t":10,"s":[0]},{"i":{"x":[0.667],"y":[1]},"o":{"x":[0.333],"y":[0]},"t":13,"s":[1]},{"i":{"x":[0.667],"y":[1]},"o":{"x":[0.333],"y":[0]},"t":35,"s":[1]},{"t":38,"s":[0]}],"ix":10},"p":{"a":0,"k":[382.151,469.05,0],"ix":2},"a":{"a":0,"k":[55,203,0],"ix":1},"s":{"a":0,"k":[100,100,100],"ix":6}},"ao":0,"shapes":[{"ty":"gr","it":[{"ind":0,"ty":"sh","ix":1,"ks":{"a":0,"k":{"i":[[0,0],[-0.901,-3.699],[-4.6,-22.399],[-1.3,-5.6],[0.1,-8],[2,-29.6],[0.7,-1.1],[1.8,-0.399],[3.2,0.6],[0.6,3.2],[-0.2,1.401],[-1.1,23.9],[2.3,8.301],[3.599,5.6],[6,26.1]],"o":[[2.4,2.9],[5,22.4],[1.2,5.601],[1.9,7.8],[-0.2,29.7],[-0.099,1.301],[-1,1.5],[-3.2,0.7],[-3.199,-0.6],[-0.199,-1.3],[3.9,-23.599],[0.4,-8.5],[-1.8,-6.4],[-14.201,-22.699],[0,0]],"v":[[26.149,-107.75],[30.75,-97.45],[26.949,-29.25],[31.649,-12.75],[33.549,11.05],[29.349,100.05],[28.449,103.75],[23.649,106.25],[13.949,107.15],[6.949,101.05],[7.149,96.95],[14.549,25.55],[12.849,0.05],[4.25,-17.95],[-35.75,-87.05]],"c":true},"ix":2},"nm":"Path 1","mn":"ADBE Vector Shape - Group","hd":false},{"ty":"fl","c":{"a":0,"k":[1,1,1,1],"ix":4},"o":{"a":0,"k":100,"ix":5},"r":1,"bm":0,"nm":"Fill 1","mn":"ADBE Vector Graphic - Fill","hd":false},{"ty":"tr","p":{"a":0,"k":[36,108],"ix":2},"a":{"a":0,"k":[0,0],"ix":1},"s":{"a":0,"k":[100,100],"ix":3},"r":{"a":0,"k":0,"ix":6},"o":{"a":0,"k":100,"ix":7},"sk":{"a":0,"k":0,"ix":4},"sa":{"a":0,"k":0,"ix":5},"nm":"Transform"}],"nm":"Group 1","np":2,"cix":2,"bm":0,"ix":1,"mn":"ADBE Vector Group","hd":false}],"ip":0,"op":77,"st":0,"bm":0},{"ddd":0,"ind":12,"ty":4,"nm":"Leg R Outlines","sr":1,"ks":{"o":{"a":0,"k":70,"ix":11},"r":{"a":1,"k":[{"i":{"x":[0.667],"y":[1]},"o":{"x":[0.333],"y":[0]},"t":10,"s":[0]},{"i":{"x":[0.667],"y":[1]},"o":{"x":[0.333],"y":[0]},"t":13,"s":[1]},{"i":{"x":[0.667],"y":[1]},"o":{"x":[0.333],"y":[0]},"t":35,"s":[1]},{"t":38,"s":[0]}],"ix":10},"p":{"a":0,"k":[343.201,460.75,0],"ix":2},"a":{"a":0,"k":[32.25,179.4,0],"ix":1},"s":{"a":0,"k":[100,100,100],"ix":6}},"ao":0,"shapes":[{"ty":"gr","it":[{"ind":0,"ty":"sh","ix":1,"ks":{"a":0,"k":{"i":[[0,0],[-6.399,-20],[0,-10.401],[1,-5.401],[0.599,-22.899],[4.201,-2.3],[1.901,-0.099],[2.5,0.401],[1.299,1.5],[-1.101,3.2],[1.9,26.7],[6.9,8.099],[3.899,3.5],[4.299,15.5]],"o":[[2.101,20.9],[3.2,9.9],[0,5.5],[-3.901,22.5],[-0.101,4.8],[-1.7,0.9],[-2.5,0.101],[-1.901,-0.3],[-2.201,-2.5],[9,-25.3],[-0.8,-10.6],[-3.399,-4],[-11.901,-10.8],[0,0]],"v":[[7.399,-95.15],[20.099,-33.65],[27,-3.35],[25,12.951],[18.2,81.049],[13.299,93.85],[7.799,95.049],[0.2,94.549],[-5,92.249],[-5,82.549],[5.899,3.35],[-1.601,-26.549],[-12.3,-37.15],[-27,-87.25]],"c":true},"ix":2},"nm":"Path 1","mn":"ADBE Vector Shape - Group","hd":false},{"ty":"fl","c":{"a":0,"k":[1,1,1,1],"ix":4},"o":{"a":0,"k":100,"ix":5},"r":1,"bm":0,"nm":"Fill 1","mn":"ADBE Vector Graphic - Fill","hd":false},{"ty":"tr","p":{"a":0,"k":[27.25,95.4],"ix":2},"a":{"a":0,"k":[0,0],"ix":1},"s":{"a":0,"k":[100,100],"ix":3},"r":{"a":0,"k":0,"ix":6},"o":{"a":0,"k":100,"ix":7},"sk":{"a":0,"k":0,"ix":4},"sa":{"a":0,"k":0,"ix":5},"nm":"Transform"}],"nm":"Group 1","np":2,"cix":2,"bm":0,"ix":1,"mn":"ADBE Vector Group","hd":false}],"ip":0,"op":77,"st":0,"bm":0},{"ddd":0,"ind":13,"ty":4,"nm":"Body Outlines","parent":9,"sr":1,"ks":{"o":{"a":0,"k":100,"ix":11},"r":{"a":1,"k":[{"i":{"x":[0.667],"y":[1]},"o":{"x":[0.333],"y":[0]},"t":10,"s":[0]},{"i":{"x":[0.667],"y":[1]},"o":{"x":[0.333],"y":[0]},"t":13,"s":[-5]},{"i":{"x":[0.667],"y":[1]},"o":{"x":[0.333],"y":[0]},"t":35,"s":[-5]},{"t":38,"s":[0]}],"ix":10},"p":{"a":0,"k":[37.6,-18,0],"ix":2},"a":{"a":0,"k":[62.4,59.3,0],"ix":1},"s":{"a":0,"k":[100,100,100],"ix":6}},"ao":0,"shapes":[{"ty":"gr","it":[{"ind":0,"ty":"sh","ix":1,"ks":{"a":0,"k":{"i":[[0,0],[-45.9,-14.3],[-4,-3.8],[0,-8.899],[2.9,-5.199],[6.6,-3.401],[11.8,-4.5],[18.5,4.201],[9.6,5.5],[16.7,9.399],[2.5,2.9],[0.5,4.601],[-2.4,8.7],[-5.5,7.6],[-9.1,2.4]],"o":[[43,21.7],[5.3,1.6],[6.4,6.1],[0,6],[-3.6,6.5],[-11.2,5.8],[-17.8,6.699],[-10.8,-2.5],[-16.8,-9.5],[-3.4,-1.9],[-3,-3.5],[-1.1,-8.999],[2.5,-9.1],[5.5,-7.6],[0,0]],"v":[[-56.05,-68.05],[80.75,-22.65],[95.45,-15.35],[103.15,9.349],[99.75,26.849],[82.75,40.75],[48.35,56.15],[-7.25,63.849],[-37.55,50.349],[-87.85,19.95],[-97.15,13.15],[-102.05,0.349],[-99.15,-26.45],[-87.65,-52.05],[-65.25,-66.35]],"c":true},"ix":2},"nm":"Path 1","mn":"ADBE Vector Shape - Group","hd":false},{"ty":"fl","c":{"a":0,"k":[1,1,1,1],"ix":4},"o":{"a":0,"k":100,"ix":5},"r":1,"bm":0,"nm":"Fill 1","mn":"ADBE Vector Graphic - Fill","hd":false},{"ty":"tr","p":{"a":0,"k":[103.4,68.3],"ix":2},"a":{"a":0,"k":[0,0],"ix":1},"s":{"a":0,"k":[100,100],"ix":3},"r":{"a":0,"k":0,"ix":6},"o":{"a":0,"k":100,"ix":7},"sk":{"a":0,"k":0,"ix":4},"sa":{"a":0,"k":0,"ix":5},"nm":"Transform"}],"nm":"Group 1","np":2,"cix":2,"bm":0,"ix":1,"mn":"ADBE Vector Group","hd":false}],"ip":0,"op":77,"st":0,"bm":0}],"markers":[]}